Metadata-Version: 2.1
Name: multialias
Version: 1.0.0
Summary: A command line tool to bulk rename files
Author: itsknk
